pccl/__init__.py
pccl-0.0.0.dist-info/METADATA
pccl-0.0.0.dist-info/WHEEL
pccl-0.0.0.dist-info/top_level.txt
pccl-0.0.0.dist-info/RECORD
