Metadata-Version: 2.4
Name: pccl
Version: 0.0.0
Summary: Coming soon
Author-email: Siddharth Singh <ssingh37@umd.edu>, Abhinav Bhatele <bhatele@cs.umd.edu>
